<?xml version="1.0" encoding="UTF-8" ?>
<!DOCTYPE mapper
 PUBLIC "-//mybatis.org//DTD Mapper 3.0//EN"
 "http://mybatis.org/dtd/mybatis-3-mapper.dtd">

<mapper namespace="com.team1.mybatis.IDocRegDAO">
 	
 	
 	<insert id="addDoc"> <!-- // [시터] 서류 등록 public int addDoc(DocRegDTO docreg); -->
	<selectKey keyProperty="doc_reg_id" resultType="String" order="BEFORE">
		SELECT 'SDOC' || LPAD(SDOC_SEQ.NEXTVAL, 4, '0') 
		FROM DUAL
	</selectKey>
	 	INSERT INTO DOC_REG(DOC_REG_ID, DOC_TYPE_ID, SIT_REG_ID, FILE_PATH)
		VALUES(#{doc_reg_id}, #{doc_type_id}, #{sit_reg_id}, #{file_path})
 	</insert> 
 	
 	
 	<update id="modifyDoc"> <!-- // [시터] 서류 수정 public int modifyDoc(DocRegDTO docreg); -->
	 	UPDATE DOC_REG
		SET DOC_TYPE_ID = #{doc_type_id}, FILE_PATH = #{file_path} 
		WHERE SIT_REG_ID = #{sit_reg_id}
 	</update>
 	
 	<!-- 
 	<delete id="removeDoc"> // [시터] 서류 삭제 public int removeDoc(DocRegDTO docreg);
	 	DELETE
		FROM DOC_REG
		WHERE SIT_REG_ID = #{sit_reg_id}
 	</delete>
 	 -->
 	 
 	<!-- 시터가 제출한 서류 목록 확인 -->
 	<select id="search" resultType="com.team1.dto.DocRegDTO"> 
	 	SELECT S.SIT_REG_ID AS SIT_REG_ID, D.DOC_REG_ID AS DOC_REG_ID, T.TYPE AS TYPE
		     , D.FILE_PATH AS FILE_PATH, D.REG_DATE AS REG_DATE
		FROM DOC_REG D
		JOIN SIT_REG S 
		  ON S.SIT_REG_ID = D.SIT_REG_ID
		JOIN DOC_TYPES T 
		  ON D.DOC_TYPE_ID = T.DOC_TYPE_ID
		JOIN SIT_BACKUP SB
		  ON S.SIT_BACKUP_ID = SB.SIT_BACKUP_ID
		WHERE S.SIT_BACKUP_ID = #{sit_backup_id}
		ORDER BY D.REG_DATE DESC
 	</select>
 	
</mapper>
