<?xml version="1.0" encoding="UTF-8" ?>
<!DOCTYPE mapper
 PUBLIC "-//mybatis.org//DTD Mapper 3.0//EN"
 "http://mybatis.org/dtd/mybatis-3-mapper.dtd">

<mapper namespace="com.team1.mybatis.IGenRegDAO">
	
	<!-- 일반 돌봄 근무 등록 -->
	<insert id="add" parameterType="com.team1.dto.GenRegDTO" keyProperty="gen_reg_id">
	<selectKey keyProperty="gen_reg_id" resultType="String" order="BEFORE">
		SELECT 'GREG' || LPAD(SEQ_GREG.NEXTVAL, 4, '0') AS gen_reg_id
		FROM DUAL
	</selectKey>
		INSERT INTO GEN_REG(GEN_REG_ID, SIT_BACKUP_ID, TITLE, START_DATE, END_DATE
		, START_TIME, END_TIME, REG_DATE, INTRODUCTION)
		VALUES(#{gen_reg_id}, #{sit_backup_id}, #{title}
		, #{start_date}, #{end_date}
		, #{start_time}, #{end_time}, SYSDATE, #{introduction})
	</insert>
	
	<!-- 일반 돌봄 근무 삭제 -->
	<delete id="remove">
		DELETE FROM GEN_REG
		WHERE GEN_REG_ID = #{gen_reg_id}
	</delete>

	<!-- 시터 근무 가능 목록 -->
	<select id="list" resultType="com.team1.dto.GenRegDTO">
		SELECT GEN_REG_ID, SIT_BACKUP_ID, TITLE, START_DATE, END_DATE
		, START_TIME, END_TIME, REG_DATE, INTRODUCTION
		FROM GEN_REG		
	</select>
	
	<!-- 전체 근무 등록 수 확인 -->
	<select id="countGen" resultType="java.lang.Integer">
		SELECT COUNT(*) AS COUNT
		FROM GEN_REG
	</select>
	
	<!-- 특정 아이디에 따른 근무 등록 파일-->
	<select id="regList" resultType="com.team1.dto.GenRegDTO">
		SELECT GEN_REG_ID, SIT_BACKUP_ID, TITLE, START_DATE, END_DATE
		, START_TIME, END_TIME, REG_DATE, INTRODUCTION
		FROM GEN_REG
		WHERE GEN_REG_ID = #{gen_reg_id}	
	</select>
	
	<!-- (부모가 보는) 1차 필터 결과 리스트 -->
	<select id="listPrimaryGenReg" resultType="com.team1.dto.GenRegDTO">
		SELECT R.GEN_REG_ID, R.NAME, R.TITLE, R.START_DATE, R.END_DATE, R.START_TIME, R.END_TIME
		     , CASE WHEN NOT EXISTS 
		                (
		                    SELECT 1
		                    FROM GEN_REQ Q
		                    WHERE R.GEN_REG_ID = Q.GEN_REG_ID
		                ) THEN '예약중'
		            ELSE '예약가능'
		            END AS STATUS
		FROM GEN_REG_POSSIBLE_VIEW R
		WHERE R.START_DATE &lt;= #{start_date}
		  AND R.END_DATE &gt;= #{end_date}
		  AND R.START_TIME &lt;= #{start_time}
		  AND R.END_TIME &gt;= #{end_time}
	</select>
	
	<!-- (부모가 보는) 1차 필터 결과 리스트 건수 -->
	<select id="countPrimaryGenReg" resultType="java.lang.Integer">
		SELECT COUNT(*) AS COUNT
		FROM GEN_REG_POSSIBLE_VIEW R
		WHERE R.START_DATE &lt;= #{start_date}
		  AND R.END_DATE &gt;= #{end_date}
		  AND R.START_TIME &lt;= #{start_time}
		  AND R.END_TIME &gt;= #{end_time}
	</select>
	
</mapper>